{
  "color": {
    "disabled": {
      "text": {
        "$light": {
          "value": "#828282",
          "description": "",
          "colorScheme": "light"
        }
      },
      "border": {
        "$light": {
          "value": "#dfdfdf",
          "description": "",
          "colorScheme": "light"
        }
      },
      "background": {
        "$light": {
          "value": "#dfdfdf",
          "description": "",
          "colorScheme": "light"
        }
      }
    },
    "active": {
      "text": {
        "$light": {
          "value": "#595959",
          "description": "",
          "colorScheme": "light"
        }
      }
    },
    "hover": {
      "text": {
        "$light": {
          "value": "#595959",
          "description": "",
          "colorScheme": "light"
        }
      }
    },
    "base": {
      "text": {
        "$light": {
          "value": "#595959",
          "description": "",
          "colorScheme": "light"
        }
      }
    }
  }
}