{
  "color": {
    "action": {
      "active": {
        "text": {
          "value": "#f2f2f2",
          "description": ""
        },
        "border": {
          "value": "#087aaa",
          "description": ""
        },
        "background": {
          "value": "#087aaa",
          "description": ""
        }
      },
      "hover": {
        "text": {
          "value": "#333333",
          "description": ""
        },
        "border": {
          "value": "#55c6f7",
          "description": ""
        },
        "background": {
          "value": "#55c6f7",
          "description": ""
        }
      },
      "base": {
        "text": {
          "value": "#333333",
          "description": ""
        },
        "border": {
          "value": "#9edffa",
          "description": ""
        },
        "background": {
          "value": "#9edffa",
          "description": ""
        }
      },
      "disabled": {
        "text": {
          "value": "#cecece",
          "description": ""
        }
      }
    }
  }
}