{
  "color": {
    "adjacent": {
      "box": {
        "background": {
          "value": "#f9aa4e",
          "comment": ""
        },
        "border": {
          "value": "#a85d06",
          "comment": ""
        },
        "text": {
          "value": "#f9aa4e",
          "comment": ""
        }
      },
      "fill": {
        "background": {
          "value": "#f9aa4e",
          "comment": ""
        },
        "border": {
          "value": "#a85d06",
          "comment": ""
        },
        "text": {
          "value": "#f5f5f5",
          "comment": ""
        }
      },
      "outline": {
        "border": {
          "value": "#fcce98",
          "comment": ""
        },
        "text": {
          "value": "#fcce98",
          "comment": ""
        }
      },
      "active": {
        "text": {
          "value": "#f5f5f5",
          "comment": ""
        },
        "border": {
          "value": "",
          "comment": ""
        },
        "background": {
          "value": "",
          "comment": ""
        }
      },
      "hover": {
        "text": {
          "value": "#333333",
          "comment": ""
        },
        "border": {
          "value": "#f9aa4e",
          "comment": ""
        },
        "background": {
          "value": "#f9aa4e",
          "comment": ""
        }
      },
      "base": {
        "text": {
          "value": "#333333",
          "comment": ""
        },
        "background": {
          "value": "#f9aa4e",
          "comment": ""
        },
        "border": {
          "value": "#f9aa4e",
          "comment": ""
        }
      },
      "disabled": {
        "text": {
          "value": "#cecece",
          "comment": ""
        }
      },
      "emphasize": {
        "value": "#f9aa4e",
        "comment": ""
      }
    }
  }
}